{
  "dataset": "D3",
  "method": "RC",
  "poison_name": "poison_random",
  "poison_dir": "data/raw/poison_random",
  "train_poison_dir": "data/raw/poison_random",
  "eval_poison_dir": "data/raw/poison_random",
  "eval_poison_same_dir": true,
  "eval_poison_split": "same_dir_random",
  "n_expert": 140,
  "n_poison": 60,
  "n_requested_poison": 60,
  "n_available_train_poison": 290,
  "n_requested_held_out_poison": 10,
  "poison_pct": 0.3,
  "irl_iters": 1000,
  "feature_version": "v1",
  "feature_names": [
    "road_coverage",
    "grass_coverage",
    "center_deviation",
    "action_nothing",
    "action_steer_left",
    "action_steer_right",
    "action_gas",
    "action_brake"
  ],
  "rc_k": 3,
  "seed": null,
  "theta": [
    0.13004339202696832,
    -0.12863906795594476,
    -0.051022638232047404,
    -1.1595530624702588,
    -1.7962180444617488,
    -0.8678384169912838,
    4.97041195427824,
    -1.1468024303549462
  ],
  "train_poison_paths": [
    "data\\raw\\poison_random\\traj_0130.npz",
    "data\\raw\\poison_random\\traj_0224.npz",
    "data\\raw\\poison_random\\traj_0057.npz",
    "data\\raw\\poison_random\\traj_0241.npz",
    "data\\raw\\poison_random\\traj_0283.npz",
    "data\\raw\\poison_random\\traj_0053.npz",
    "data\\raw\\poison_random\\traj_0120.npz",
    "data\\raw\\poison_random\\traj_0078.npz",
    "data\\raw\\poison_random\\traj_0112.npz",
    "data\\raw\\poison_random\\traj_0074.npz",
    "data\\raw\\poison_random\\traj_0066.npz",
    "data\\raw\\poison_random\\traj_0096.npz",
    "data\\raw\\poison_random\\traj_0169.npz",
    "data\\raw\\poison_random\\traj_0144.npz",
    "data\\raw\\poison_random\\traj_0020.npz",
    "data\\raw\\poison_random\\traj_0123.npz",
    "data\\raw\\poison_random\\traj_0010.npz",
    "data\\raw\\poison_random\\traj_0134.npz",
    "data\\raw\\poison_random\\traj_0244.npz",
    "data\\raw\\poison_random\\traj_0259.npz",
    "data\\raw\\poison_random\\traj_0051.npz",
    "data\\raw\\poison_random\\traj_0146.npz",
    "data\\raw\\poison_random\\traj_0153.npz",
    "data\\raw\\poison_random\\traj_0268.npz",
    "data\\raw\\poison_random\\traj_0282.npz",
    "data\\raw\\poison_random\\traj_0231.npz",
    "data\\raw\\poison_random\\traj_0230.npz",
    "data\\raw\\poison_random\\traj_0028.npz",
    "data\\raw\\poison_random\\traj_0181.npz",
    "data\\raw\\poison_random\\traj_0030.npz",
    "data\\raw\\poison_random\\traj_0110.npz",
    "data\\raw\\poison_random\\traj_0069.npz",
    "data\\raw\\poison_random\\traj_0173.npz",
    "data\\raw\\poison_random\\traj_0284.npz",
    "data\\raw\\poison_random\\traj_0197.npz",
    "data\\raw\\poison_random\\traj_0081.npz",
    "data\\raw\\poison_random\\traj_0190.npz",
    "data\\raw\\poison_random\\traj_0109.npz",
    "data\\raw\\poison_random\\traj_0115.npz",
    "data\\raw\\poison_random\\traj_0213.npz",
    "data\\raw\\poison_random\\traj_0233.npz",
    "data\\raw\\poison_random\\traj_0042.npz",
    "data\\raw\\poison_random\\traj_0100.npz",
    "data\\raw\\poison_random\\traj_0175.npz",
    "data\\raw\\poison_random\\traj_0289.npz",
    "data\\raw\\poison_random\\traj_0079.npz",
    "data\\raw\\poison_random\\traj_0273.npz",
    "data\\raw\\poison_random\\traj_0089.npz",
    "data\\raw\\poison_random\\traj_0113.npz",
    "data\\raw\\poison_random\\traj_0036.npz",
    "data\\raw\\poison_random\\traj_0040.npz",
    "data\\raw\\poison_random\\traj_0139.npz",
    "data\\raw\\poison_random\\traj_0182.npz",
    "data\\raw\\poison_random\\traj_0131.npz",
    "data\\raw\\poison_random\\traj_0194.npz",
    "data\\raw\\poison_random\\traj_0279.npz",
    "data\\raw\\poison_random\\traj_0160.npz",
    "data\\raw\\poison_random\\traj_0063.npz",
    "data\\raw\\poison_random\\traj_0099.npz",
    "data\\raw\\poison_random\\traj_0126.npz"
  ],
  "held_out_poison_paths": [
    "data\\raw\\poison_random\\traj_0261.npz",
    "data\\raw\\poison_random\\traj_0086.npz",
    "data\\raw\\poison_random\\traj_0137.npz",
    "data\\raw\\poison_random\\traj_0031.npz",
    "data\\raw\\poison_random\\traj_0037.npz",
    "data\\raw\\poison_random\\traj_0073.npz",
    "data\\raw\\poison_random\\traj_0200.npz",
    "data\\raw\\poison_random\\traj_0007.npz",
    "data\\raw\\poison_random\\traj_0285.npz",
    "data\\raw\\poison_random\\traj_0062.npz"
  ],
  "mean_expert_score": 2.5175329817342504,
  "mean_poison_score": -0.0206961298089413,
  "separation": 2.538229111543192,
  "auc": 1.0,
  "n_held_out_expert": 50,
  "n_held_out_poison": 10,
  "expert_scores": [
    2.4650383387037142,
    2.169222109395701,
    1.9632926295534598,
    1.847492845368605,
    2.6029688928128176,
    2.0830874683826357,
    1.498691979449656,
    1.9626557937323983,
    3.122573513076142,
    2.755598297054989,
    1.4555719390693709,
    2.497542623009589,
    2.278471777027401,
    3.3592839580462504,
    2.8796951485316886,
    2.890923149660239,
    2.4055620503587445,
    3.0559793770343906,
    3.1813951311155795,
    2.91773979657441,
    2.396087933479366,
    3.122846874453434,
    2.6184649330470053,
    2.4502215487177708,
    1.7185069676982365,
    2.812630726316938,
    3.4176171894210174,
    1.9099129941476063,
    2.372283508632977,
    3.168453467398614,
    2.0949429891113707,
    3.1648161654461027,
    3.4547670753078785,
    2.6694590324619116,
    2.7994053166249335,
    2.9538635189836024,
    2.541339828335038,
    3.132067546551902,
    2.0177765941645256,
    1.8083424665549486,
    2.2526096596800453,
    3.048967034221659,
    1.6349571147867796,
    2.113632863058145,
    3.078414034309369,
    2.21722917467315,
    3.0384035140541266,
    2.4285625341786794,
    2.178957160409704,
    1.8683225025278978
  ],
  "poison_scores": [
    -0.03948125718961226,
    0.0377693099494234,
    0.03718883717712518,
    -0.07249126858586508,
    -0.04536385889620875,
    -0.04653372087333574,
    0.026969196308244903,
    -0.03171059391801545,
    -0.01842885745712597,
    -0.05487908460404323
  ]
}